{
  "date": "2026-07-10",
  "word": "martyr",
  "meaningEn": "One who willingly accepts being put to death for adhering openly to one's religious beliefs; notably, saints canonized after martyrdom.",
  "meaningSi": "කෙනෙකුගේ ආගමික විශ්වාසයන්ට විවෘතව බැඳී සිටීම නිසා කැමැත්තෙන්ම මරණයට පත් කිරීම පිළිගන්නා තැනැත්තා; විශේෂයෙන්, සාන්තුවරයන් දිවි පිදීමෙන් පසු කැනොනිස් කර ඇත.",
  "phonetic": "/ˈmɐːtə(ɹ)/",
  "audio": "https://api.dictionaryapi.dev/media/pronunciations/en/martyr-uk.mp3",
  "usage": [
    {
      "en": "I am learning the word \"martyr\" today.",
      "si": "අද මම \"මාරයා\" යන වචනය ඉගෙන ගනිමි."
    },
    {
      "en": "Can you use \"martyr\" in a sentence?",
      "si": "ඔබට වචනයක් තුළ \"මාරයා\" භාවිතා කළ හැකිද?"
    },
    {
      "en": "This word \"martyr\" is useful in daily English.",
      "si": "දෛනික ඉංග් රීසි භාෂාවේදී \"මාතර\" යන වචනය ප් රයෝජනවත් වේ."
    }
  ]
}